barbuilder/.DS_Store
barbuilder/__about__.py
barbuilder/__init__.py
barbuilder/base.py
barbuilder/menu.py
barbuilder/utils.py
barbuilder-0.3.2.dist-info/METADATA
barbuilder-0.3.2.dist-info/WHEEL
barbuilder-0.3.2.dist-info/licenses/LICENSE
barbuilder-0.3.2.dist-info/RECORD
