Metadata-Version: 2.1
Name: barbuilder
Version: 0.3.2
Summary: Utility library for building SwiftBar-like plugins
Project-URL: Documentation, https://github.com/unknown/barbuilder#readme
Project-URL: Issues, https://github.com/unknown/barbuilder/issues
Project-URL: Source, https://github.com/unknown/barbuilder
Author-email: Dave Chevell <chevell@gmail.com>
License-Expression: MIT
License-File: LICENSE
Classifier: Development Status :: 4 - Beta
Classifier: Programming Language :: Python
Classifier: Programming Language :: Python :: 3.7
Classifier: Programming Language :: Python :: 3.8
Classifier: Programming Language :: Python :: 3.9
Classifier: Programming Language :: Python :: 3.10
Classifier: Programming Language :: Python :: 3.11
Classifier: Programming Language :: Python :: Implementation :: CPython
Classifier: Programming Language :: Python :: Implementation :: PyPy
Requires-Python: >=3.7
